pybinrpc/__init__.py
pybinrpc/client.py
pybinrpc/const.py
pybinrpc/exceptions.py
pybinrpc/py.typed
pybinrpc/server.py
pybinrpc/support.py
pybinrpc-2025.10.1.dist-info/licenses/LICENSE
pybinrpc_support/__init__.py
pybinrpc_support/server.py
pybinrpc-2025.10.1.dist-info/METADATA
pybinrpc-2025.10.1.dist-info/WHEEL
pybinrpc-2025.10.1.dist-info/top_level.txt
pybinrpc-2025.10.1.dist-info/RECORD
