Metadata-Version: 2.4
Name: pybinrpc
Version: 2025.10.1
Summary: Python implementation of the Bin-RPC protocol.
Home-page: https://github.com/sukramj/pybinrpc
Author-email: SukramJ <sukramj@icloud.com>
License: MIT License
Project-URL: Source Code, https://github.com/sukramj/pybinrpc
Project-URL: Bug Reports, https://github.com/sukramj/pybinrpc/issues
Project-URL: Docs: Dev, https://github.com/sukramj/pybinrpc
Project-URL: Forum, https://github.com/sukramj/pybinrpc/discussions
Keywords: home,automation,homematic,cuxd
Classifier: Development Status :: 5 - Production/Stable
Classifier: Intended Audience :: End Users/Desktop
Classifier: Intended Audience :: Developers
Classifier: License :: OSI Approved :: MIT License
Classifier: Operating System :: OS Independent
Classifier: Programming Language :: Python :: 3.13
Classifier: Topic :: Home Automation
Requires-Python: >=3.13.0
License-File: LICENSE
Dynamic: license-file
